sdxdatamodel/__init__.py
sdxdatamodel/models/__init__.py
sdxdatamodel/models/connection.py
sdxdatamodel/models/link.py
sdxdatamodel/models/link_measurement_period.py
sdxdatamodel/models/location.py
sdxdatamodel/models/node.py
sdxdatamodel/models/port.py
sdxdatamodel/models/service.py
sdxdatamodel/models/topology.py
sdxdatamodel/parsing/__init__.py
sdxdatamodel/parsing/connectionhandler.py
sdxdatamodel/parsing/exceptions.py
sdxdatamodel/parsing/linkhandler.py
sdxdatamodel/parsing/locationhandler.py
sdxdatamodel/parsing/nodehandler.py
sdxdatamodel/parsing/porthandler.py
sdxdatamodel/parsing/servicehandler.py
sdxdatamodel/parsing/topologyhandler.py
sdxdatamodel/sdxdatamodel.egg-info/PKG-INFO
sdxdatamodel/sdxdatamodel.egg-info/SOURCES.txt
sdxdatamodel/sdxdatamodel.egg-info/dependency_links.txt
sdxdatamodel/sdxdatamodel.egg-info/requires.txt
sdxdatamodel/sdxdatamodel.egg-info/top_level.txt
sdxdatamodel/topologymanager/__init__.py
sdxdatamodel/topologymanager/grenmlconverter.py
sdxdatamodel/topologymanager/manager.py
sdxdatamodel/topologymanager/temanager.py
sdxdatamodel/validation/__init__.py
sdxdatamodel/validation/connectionvalidator.py
sdxdatamodel/validation/topologyvalidator.py
sdxdatamodel-0.0.1.dist-info/LICENSE
sdxdatamodel-0.0.1.dist-info/WHEEL
sdxdatamodel-0.0.1.dist-info/METADATA
sdxdatamodel-0.0.1.dist-info/RECORD
