Metadata-Version: 2.1
Name: sdxdatamodel
Version: 0.0.1
Summary: Topology and request description data model in JSON
Author-email: "Y. Xin" <yxin@renci.org>
Requires-Python: >=3.6
Classifier: Programming Language :: Python :: 3
Classifier: License :: OSI Approved :: MIT License
Classifier: Operating System :: OS Independent
Requires-Dist: grenml
Requires-Dist: networkx
Requires-Dist: pytest >= 7.1.2 ; extra == "test"
Requires-Dist: pytest-cov >= 3.0.0 ; extra == "test"
Requires-Dist: matplotlib ; extra == "test"
Project-URL: Home, https://github.com/atlanticwave-sdx/datamodel
Project-URL: Issues, https://github.com/atlanticwave-sdx/datamodel/issues
Provides-Extra: test
